{
  "version": "7",
  "dialect": "postgresql",
  "entries": [
    {
      "idx": 0,
      "version": "7",
      "when": 1729665956101,
      "tag": "0000_windy_bishop",
      "breakpoints": true
    },
    {
      "idx": 1,
      "version": "7",
      "when": 1729666563103,
      "tag": "0001_aromatic_diamondback",
      "breakpoints": true
    },
    {
      "idx": 2,
      "version": "7",
      "when": 1729673718836,
      "tag": "0002_pretty_captain_britain",
      "breakpoints": true
    },
    {
      "idx": 3,
      "version": "7",
      "when": 1729973449568,
      "tag": "0003_ancient_stingray",
      "breakpoints": true
    },
    {
      "idx": 4,
      "version": "7",
      "when": 1729974188709,
      "tag": "0004_harsh_surge",
      "breakpoints": true
    },
    {
      "idx": 9,
      "version": "7",
      "when": 1730774186008,
      "tag": "0009_workable_tattoo",
      "breakpoints": true
    }
  ]
}